rtl/defines.vh
`ifndef DEFINES_VH
`define DEFINES_VH

// CORECT: Spatiu intre nume si valoare. FARA egal, FARA punct si virgula.
`define KYBER_Q 12'd3329
`define DWIDTH 12

`endif

rtl/arithmetic/mod_sub.v
`include "defines.vh"

module mod_sub (
    input  wire [`DWIDTH-1:0] a,
    input  wire [`DWIDTH-1:0] b,
    output wire [`DWIDTH-1:0] out
);

    wire [`DWIDTH:0] diff_raw;
    wire [`DWIDTH:0] diff_add_q;

    // 1. Calculam a - b (standard)
    assign diff_raw = a - b;

    // 2. Calculam a - b + 3329 (pentru cazul in care a < b)
    assign diff_add_q = a + `KYBER_Q - b;

    // 3. Alegem rezultatul:
    // Daca a >= b, facem scaderea normala.
    // Daca a < b, folosim varianta cu +3329 ca sa nu avem numar negativ.
    assign out = (a >= b) ? diff_raw[`DWIDTH-1:0] : diff_add_q[`DWIDTH-1:0];

endmodule

rtl/arithmetic/mod_add.v
`include "defines.vh"

module mod_add (
    input  wire [`DWIDTH-1:0] a,
    input  wire [`DWIDTH-1:0] b,
    output wire [`DWIDTH-1:0] out
);

    wire [`DWIDTH:0] sum_raw;    // Suma initiala (poate depasi 12 biti)
    wire [`DWIDTH:0] sum_sub_q;  // Suma din care scadem q (3329)

    // 1. Calculam a + b
    assign sum_raw = a + b;

    // 2. Calculam (a + b) - 3329
    assign sum_sub_q = sum_raw - `KYBER_Q;

    // 3. Alegem rezultatul:
    // Daca suma >= 3329, trebuie sa scadem 3329 (rezultatul e sum_sub_q).
    // Altfel, pastram suma simpla.
    assign out = (sum_raw >= `KYBER_Q) ? sum_sub_q[`DWIDTH-1:0] : sum_raw[`DWIDTH-1:0];

endmodule

rtl/arithmetic/montgomery_mult.v
`include "defines.vh"

module montgomery_mult (
    input  wire [`DWIDTH-1:0] a,
    input  wire [`DWIDTH-1:0] b,
    output wire [`DWIDTH-1:0] out
);

    // Constanta QINV = -3329^(-1) mod 2^16
    // Pentru q=3329, QINV este 62209 (sau -3327 in complement fata de 2 pe 16 biti)
    localparam [15:0] QINV = 16'd62209; 

    // Produsul poate avea maxim 24 de biti (12 * 12)
    wire signed [23:0] prod;
    
    // Variabile intermediare pentru reducerea Montgomery
    wire signed [15:0] m;
    wire signed [27:0] t; // Avem nevoie de spatiu extra pentru adunare
    wire signed [11:0] res_raw;

    // 1. Calculul produsului: A * B
    // Folosim $signed pentru a trata corect numerele in aritmetica
    assign prod = $signed(a) * $signed(b);

    // 2. Calculul factorului de reducere m = (prod * QINV) mod R
    // Aici ne intereseaza doar cei mai putin semnificativi 16 biti
    assign m = prod[15:0] * $signed(QINV);

    // 3. Calculul t = (prod + m * Q) / 2^16
    // Formula Montgomery: (prod + m*Q) va fi intotdeauna divizibil cu 2^16
    // ">>> 16" este shiftare aritmetica (impartire la 65536)
    assign t = (prod + m * $signed(`KYBER_Q)) >>> 16;

    // 4. Rezultatul final (t poate fi inca >= Q, deci trebuie redus)
    // Deoarece lucram cu signed, t poate fi negativ sau pozitiv
    assign res_raw = t[11:0];
    
    // Verificam daca trebuie sa ajustam rezultatul
    // Nota: Aceasta este o implementare simplificata. In hardware real, 
    // pasul de scadere conditionala se face adesea in ciclul urmator sau pipeline.
    assign out = (t >= $signed(`KYBER_Q)) ? (res_raw - `KYBER_Q) : res_raw;

endmodule

rtl/ntt/butterfly.v
`include "defines.vh"

module butterfly (
    input  wire [`DWIDTH-1:0] a,
    input  wire [`DWIDTH-1:0] b,
    input  wire [`DWIDTH-1:0] zeta, // Factorul "twiddle"
    output wire [`DWIDTH-1:0] out_a,
    output wire [`DWIDTH-1:0] out_b
);

    wire [`DWIDTH-1:0] t; 

    // 1. Calculam t = b * zeta (Montgomery)
    montgomery_mult mult_unit (
        .a(b),
        .b(zeta),
        .out(t)
    );

    // 2. Calculam out_a = a + t
    mod_add add_unit (
        .a(a),
        .b(t),
        .out(out_a)
    );

    // 3. Calculam out_b = a - t
    mod_sub sub_unit (
        .a(a),
        .b(t),
        .out(out_b)
    );

endmodule

rtl/bram/dual_port_ram.v
// rtl/bram/dual_port_ram.v
`include "defines.vh"

module dual_port_ram #(
    parameter ADDR_WIDTH = 8 // 2^8 = 256 locatii (cat e n la Kyber)
)(
    input wire clk,
    input wire we,                      // Write Enable (semnal de scriere)
    input wire [ADDR_WIDTH-1:0] addr_a, // Adresa A
    input wire [ADDR_WIDTH-1:0] addr_b, // Adresa B
    input wire [`DWIDTH-1:0] din_a,     // Date de intrare (pentru scriere la adresa A)
    output reg [`DWIDTH-1:0] dout_a,    // Date de iesire A
    output reg [`DWIDTH-1:0] dout_b     // Date de iesire B
);

    // Definim memoria propriu-zisa (un vector de registre)
    reg [`DWIDTH-1:0] ram [0:(1<<ADDR_WIDTH)-1];

    // Portul A (Citire si Scriere)
    always @(posedge clk) begin
        if (we) begin
            ram[addr_a] <= din_a;
            dout_a <= din_a; // Optional: la scriere scoatem data pe iesire
        end else begin
            dout_a <= ram[addr_a];
        end
    end

    // Portul B (Doar Citire - pentru al doilea operand al Butterfly-ului)
    always @(posedge clk) begin
        dout_b <= ram[addr_b];
    end

endmodule

rtl/ntt/ntt_core.v
// rtl/ntt/ntt_core.v
`include "defines.vh"

module ntt_core (
    input  wire clk,
    input  wire rst,
    input  wire start,             // Semnal de start
    output reg  done,              // Semnal cand terminam
    // Porturi de debug (ca sa putem scrie date initiale din testbench)
    input  wire ext_we,
    input  wire [7:0] ext_addr,
    input  wire [`DWIDTH-1:0] ext_data,
    output wire [`DWIDTH-1:0] debug_out
);

    // --- Semnale Interne ---
    reg [7:0] read_addr_a, read_addr_b; // Adresele de citire
    reg [7:0] write_addr_a, write_addr_b; // Adresele de scriere
    reg we_ram; // Write Enable pentru RAM intern

    wire [`DWIDTH-1:0] ram_out_a, ram_out_b; // Ce citim din RAM
    wire [`DWIDTH-1:0] butt_out_a, butt_out_b; // Ce iese din Butterfly
    
    // Zeta (Twiddle Factor) - Hardcodam o valoare pt test
    reg [`DWIDTH-1:0] current_zeta; 

    // --- 1. Instantierea MEMORIEI (BRAM) ---
    // Folosim un multiplexor: Daca ext_we e activ (scriem din testbench), folosim adresele externe.
    // Daca nu, folosim adresele interne generate de FSM.
    dual_port_ram #(.ADDR_WIDTH(8)) memory_unit (
        .clk(clk),
        .we(ext_we || we_ram), // Scriem daca vrea testbench-ul SAU vrea algoritmul
        .addr_a(ext_we ? ext_addr : (we_ram ? write_addr_a : read_addr_a)),
        .addr_b(read_addr_b), // Portul B e doar de citire in acest design simplu
        .din_a(ext_we ? ext_data : butt_out_a), // Scriem data externa SAU rezultatul A
        // Nota: Scrierea portului B simultan ar necesita un RAM true-dual-port de scriere. 
        // Aici simplificam scriind pe rand sau modificand arhitectura.
        // Pentru demo, vom scrie doar rezultatul A.
        .dout_a(ram_out_a),
        .dout_b(ram_out_b)
    );
    
    assign debug_out = ram_out_a;

    // --- 2. Instantierea UNITATII BUTTERFLY ---
    butterfly compute_unit (
        .a(ram_out_a),
        .b(ram_out_b),
        .zeta(current_zeta),
        .out_a(butt_out_a),
        .out_b(butt_out_b)
    );

    // --- 3. STATE MACHINE (Control Unit) ---
    // Simplu: Asteapta START -> Citeste adresa 0 si 1 -> Calculeaza -> Scrie inapoi -> GATA
    
    localparam STATE_IDLE  = 0;
    localparam STATE_READ  = 1;
    localparam STATE_CALC  = 2; // O asteptare mica pt propagare
    localparam STATE_WRITE = 3;
    localparam STATE_DONE  = 4;

    reg [2:0] state;

    always @(posedge clk or posedge rst) begin
        if (rst) begin
            state <= STATE_IDLE;
            done <= 0;
            we_ram <= 0;
            read_addr_a <= 0; read_addr_b <= 0;
            current_zeta <= 12'd10; // Valoare dummy
        end else begin
            case (state)
                STATE_IDLE: begin
                    done <= 0;
                    we_ram <= 0;
                    if (start) state <= STATE_READ;
                end

                STATE_READ: begin
                    // Setam adresele pentru a citi primii doi coeficienti
                    read_addr_a <= 8'd0;
                    read_addr_b <= 8'd1;
                    state <= STATE_CALC;
                end

                STATE_CALC: begin
                    // Datele ies din RAM, trec prin Butterfly (combinational)
                    // Rezultatul este deja la butt_out_a/b.
                    // Pregatim scrierea.
                    state <= STATE_WRITE;
                end

                STATE_WRITE: begin
                    // Scriem rezultatul A inapoi la adresa 0
                    write_addr_a <= 8'd0;
                    we_ram <= 1; 
                    // (Intr-o implementare completa am scrie si B la adresa 1 in ciclul urmator)
                    state <= STATE_DONE;
                end

                STATE_DONE: begin
                    we_ram <= 0;
                    done <= 1;
                    state <= STATE_IDLE;
                end
            endcase
        end
    end

endmodule

tb/tb_ntt_core.v
// tb/tb_ntt_core.v
`timescale 1ns / 1ps
`include "defines.vh"

module tb_ntt_core;

    reg clk, rst, start;
    wire done;
    
    // Semnale pentru incarcarea datelor de test
    reg ext_we;
    reg [7:0] ext_addr;
    reg [`DWIDTH-1:0] ext_data;
    wire [`DWIDTH-1:0] debug_data;

    // Instantiem Core-ul (Top Level)
    ntt_core dut (
        .clk(clk),
        .rst(rst),
        .start(start),
        .done(done),
        .ext_we(ext_we),
        .ext_addr(ext_addr),
        .ext_data(ext_data),
        .debug_out(debug_data)
    );

    // Generator de ceas
    always #5 clk = ~clk;

    initial begin
        $dumpfile("ntt_core_test.vcd");
        $dumpvars(0, tb_ntt_core);

        // Initializare
        clk = 0; rst = 1; start = 0; ext_we = 0;
        #20;
        rst = 0;

        $display("=== 1. Incarcare Memorie (Coeficienti Initiali) ===");
        // Scriem valoarea 100 la adresa 0
        ext_we = 1; ext_addr = 0; ext_data = 12'd100; #10;
        // Scriem valoarea 50 la adresa 1
        ext_we = 1; ext_addr = 1; ext_data = 12'd50;  #10;
        ext_we = 0; // Oprim scrierea

        $display("=== 2. Pornire Procesare NTT ===");
        start = 1;
        #10;
        start = 0;

        // Asteptam sa termine (DONE signal)
        wait(done);
        $display("[INFO] Procesare terminata (Done signal primit).");

        $display("=== 3. Verificare Rezultate ===");
        // Citim memoria la adresa 0
        // Ne asteptam ca valoarea sa fie modificata de Butterfly
        // Butterfly face: A_nou = A + B*zeta. 
        // Daca memoria s-a schimbat din 100 in altceva, circuitul merge!
        #10;
        
        // Putem verifica doar vizual in simulator sau logic aici
        // Daca hardware-ul merge, la adresa 0 nu mai trebuie sa fie 100.
        
        // Citire "manuala" prin portul de debug (setam ext_we pe 0 si adresa)
        ext_addr = 0;
        #10;
        $display("Adresa 0 (Initial 100) -> Acum este: %d", debug_data);
        
        if (debug_data !== 12'd100) 
            $display("[PASS] Memoria a fost actualizata de NTT Core!");
        else 
            $display("[FAIL] Memoria a ramas neschimbata.");

        $finish;
    end

endmodule

ntt_core_test.vcd
$date
	Tue Dec 16 14:54:50 2025
$end
$version
	Icarus Verilog
$end
$timescale
	1ps
$end
$scope module tb_ntt_core $end
$var wire 1 ! done $end
$var wire 12 " debug_data [11:0] $end
$var reg 1 # clk $end
$var reg 8 $ ext_addr [7:0] $end
$var reg 12 % ext_data [11:0] $end
$var reg 1 & ext_we $end
$var reg 1 ' rst $end
$var reg 1 ( start $end
$scope module dut $end
$var wire 1 # clk $end
$var wire 12 ) debug_out [11:0] $end
$var wire 8 * ext_addr [7:0] $end
$var wire 12 + ext_data [11:0] $end
$var wire 1 & ext_we $end
$var wire 1 ' rst $end
$var wire 1 ( start $end
$var wire 12 , ram_out_b [11:0] $end
$var wire 12 - ram_out_a [11:0] $end
$var wire 12 . butt_out_b [11:0] $end
$var wire 12 / butt_out_a [11:0] $end
$var parameter 32 0 STATE_CALC $end
$var parameter 32 1 STATE_DONE $end
$var parameter 32 2 STATE_IDLE $end
$var parameter 32 3 STATE_READ $end
$var parameter 32 4 STATE_WRITE $end
$var reg 12 5 current_zeta [11:0] $end
$var reg 1 ! done $end
$var reg 8 6 read_addr_a [7:0] $end
$var reg 8 7 read_addr_b [7:0] $end
$var reg 3 8 state [2:0] $end
$var reg 1 9 we_ram $end
$var reg 8 : write_addr_a [7:0] $end
$scope module compute_unit $end
$var wire 12 ; zeta [11:0] $end
$var wire 12 < t [11:0] $end
$var wire 12 = out_b [11:0] $end
$var wire 12 > out_a [11:0] $end
$var wire 12 ? b [11:0] $end
$var wire 12 @ a [11:0] $end
$scope module add_unit $end
$var wire 13 A sum_sub_q [12:0] $end
$var wire 13 B sum_raw [12:0] $end
$var wire 12 C out [11:0] $end
$var wire 12 D b [11:0] $end
$var wire 12 E a [11:0] $end
$upscope $end
$scope module mult_unit $end
$var wire 12 F b [11:0] $end
$var wire 28 G t [27:0] $end
$var wire 12 H res_raw [11:0] $end
$var wire 24 I prod [23:0] $end
$var wire 12 J out [11:0] $end
$var wire 16 K m [15:0] $end
$var wire 12 L a [11:0] $end
$var parameter 16 M QINV $end
$upscope $end
$scope module sub_unit $end
$var wire 12 N b [11:0] $end
$var wire 12 O out [11:0] $end
$var wire 13 P diff_raw [12:0] $end
$var wire 13 Q diff_add_q [12:0] $end
$var wire 12 R a [11:0] $end
$upscope $end
$upscope $end
$scope module memory_unit $end
$var wire 8 S addr_a [7:0] $end
$var wire 8 T addr_b [7:0] $end
$var wire 1 # clk $end
$var wire 12 U din_a [11:0] $end
$var wire 1 V we $end
$var parameter 32 W ADDR_WIDTH $end
$var reg 12 X dout_a [11:0] $end
$var reg 12 Y dout_b [11:0] $end
$upscope $end
$upscope $end
$upscope $end
$enddefinitions $end
$comment Show the parameter values. $end
$dumpall
b1000 W
b1111001100000001 M
b11 4
b1 3
b0 2
b100 1
b10 0
$end
#0
$dumpvars
bx Y
bx X
0V
bx U
b0 T
b0 S
bx R
bx Q
bx P
bx O
bx N
bx L
bx K
bx J
bx I
bx H
bx G
b1010 F
bx E
bx D
bx C
bx B
bx A
bx @
bx ?
bx >
bx =
bx <
b1010 ;
bx :
09
b0 8
b0 7
b0 6
b1010 5
bx /
bx .
bx -
bx ,
bx +
bx *
bx )
0(
1'
0&
bx %
bx $
0#
bx "
0!
$end
#5000
1#
#10000
0#
#15000
1#
#20000
1V
b1100100 U
0#
b1100100 %
b1100100 +
b0 $
b0 *
1&
0'
#25000
b1100100 "
b1100100 )
b1100100 -
b1100100 @
b1100100 E
b1100100 R
b1100100 X
1#
#30000
b110010 U
b1 S
0#
b110010 %
b110010 +
b1 $
b1 *
#35000
b101011101000 .
b101011101000 =
b101011101000 O
b1001111101 /
b1001111101 >
b1001111101 C
b1110111100111 P
b101011101000 Q
b1010101111100 A
b1001111101 B
b1001001011 <
b1001001011 D
b1001001011 J
b1001001011 N
b111101001100 H
b1111111111111111111101001100 G
b11101111101000 K
b1111101000 I
b1100100 ,
b1100100 ?
b1100100 L
b1100100 Y
b110010 "
b110010 )
b110010 -
b110010 @
b110010 E
b110010 R
b110010 X
1#
#40000
0V
b0 S
b1001111101 U
0#
1(
0&
#45000
b1010101111 U
b101100011010 .
b101100011010 =
b101100011010 O
b1010101111 /
b1010101111 >
b1010101111 C
b101100011010 Q
b1111000011001 P
b1010110101110 A
b1010101111 B
b1100100 "
b1100100 )
b1100100 -
b1100100 @
b1100100 E
b1100100 R
b1100100 X
b1 8
1#
#50000
0#
0(
#55000
b10 8
b1 7
b1 T
1#
#60000
0#
#65000
b10010001000 U
b100101000001 .
b100101000001 =
b100101000001 O
b10010001000 /
b10010001000 >
b10010001000 C
b1110001000000 P
b100101000001 Q
b1011110000111 A
b10010001000 B
b10000100100 <
b10000100100 D
b10000100100 J
b10000100100 N
b100100101 H
b100100101 G
b1001110111110100 K
b111110100 I
b110010 ,
b110010 ?
b110010 L
b110010 Y
b11 8
1#
#70000
0#
#75000
1V
b100 8
19
b0 :
1#
#80000
0#
#85000
b100010101100 U
b100010101100 /
b100010101100 >
b100010101100 C
b1100100 .
b1100100 =
b1100100 O
0V
b110101100101 Q
b1100100 P
b1101110101011 A
b100010101100 B
b10010001000 "
b10010001000 )
b10010001000 -
b10010001000 @
b10010001000 E
b10010001000 R
b10010001000 X
b0 8
1!
09
1#
#90000
0#
#95000
0!
1#
b0 $
b0 *
